{"openapi":"3.0.0","paths":{"/api/v1/whatsapp/webhook":{"get":{"operationId":"WhatsappController_verifyWebhook","parameters":[{"name":"hub.mode","required":true,"in":"query","schema":{"type":"string"}},{"name":"hub.verify_token","required":true,"in":"query","schema":{"type":"string"}},{"name":"hub.challenge","required":true,"in":"query","schema":{"type":"string"}}],"responses":{"200":{"description":""}},"tags":["WhatsApp"]},"post":{"operationId":"WhatsappController_handleWebhook","parameters":[{"name":"x-hub-signature-256","required":true,"in":"header","schema":{"type":"string"}}],"responses":{"200":{"description":""}},"tags":["WhatsApp"]}},"/api/payments":{"post":{"operationId":"PaymentsController_createRequest","parameters":[],"requestBody":{"required":true,"content":{"application/json":{"schema":{"$ref":"#/components/schemas/CreatePaymentRequestDto"}}}},"responses":{"201":{"description":""}},"security":[{"bearer":[]}],"tags":["Payments"]},"get":{"operationId":"PaymentsController_getPayments","parameters":[{"name":"orderCode","required":true,"in":"query","schema":{"type":"string"}}],"responses":{"200":{"description":""}},"security":[{"bearer":[]}],"tags":["Payments"]}},"/api/payments/page":{"get":{"operationId":"PaymentsController_getPage","parameters":[{"name":"orderCode","required":true,"in":"query","schema":{"type":"string"}}],"responses":{"200":{"description":""}},"security":[{"bearer":[]}],"tags":["Payments"]}},"/api/payments/paystack/webhook":{"post":{"operationId":"PaymentsController_paystackWebhook","parameters":[{"name":"x-paystack-signature","required":true,"in":"header","schema":{"type":"string"}}],"responses":{"201":{"description":""}},"tags":["Payments"]}},"/api/winnsen/events":{"post":{"operationId":"WinnsenController_dispatch","parameters":[],"requestBody":{"required":true,"content":{"application/json":{"schema":{"$ref":"#/components/schemas/WinnsenActionDto"}}}},"responses":{"201":{"description":""}},"tags":["Winnsen"]}},"/api/locker/open-door":{"post":{"operationId":"LockerCommandsController_openDoor","parameters":[{"name":"x-api-key","in":"header","description":"WINNSEN_INBOUND_API_KEY","required":true,"schema":{"type":"string"}}],"requestBody":{"required":true,"content":{"application/json":{"schema":{"$ref":"#/components/schemas/OpenDoorDto"}}}},"responses":{"201":{"description":""}},"summary":"Queue a remote open-door command for a terminal","tags":["Locker Commands"]}},"/api/locker/commands":{"get":{"operationId":"LockerCommandsController_getCommands","parameters":[{"name":"x-api-key","in":"header","description":"WINNSEN_INBOUND_API_KEY","required":true,"schema":{"type":"string"}},{"name":"lockerSN","required":true,"in":"query","schema":{"type":"string"}}],"responses":{"200":{"description":""}},"summary":"Poll for pending commands (called by terminal)","tags":["Locker Commands"]}},"/api/locker/commands/{id}/ack":{"post":{"operationId":"LockerCommandsController_ackCommand","parameters":[{"name":"x-api-key","in":"header","description":"WINNSEN_INBOUND_API_KEY","required":true,"schema":{"type":"string"}},{"name":"id","required":true,"in":"path","schema":{"type":"string"}}],"requestBody":{"required":true,"content":{"application/json":{"schema":{"$ref":"#/components/schemas/AckCommandDto"}}}},"responses":{"201":{"description":""}},"summary":"Acknowledge a command after execution (called by terminal)","tags":["Locker Commands"]}},"/api/customer/auth/request-otp":{"post":{"operationId":"CustomerAuthController_requestOtp","parameters":[],"requestBody":{"required":true,"content":{"application/json":{"schema":{"$ref":"#/components/schemas/RequestOtpDto"}}}},"responses":{"201":{"description":""}},"tags":["Customer / Auth"]}},"/api/customer/auth/login":{"post":{"operationId":"CustomerAuthController_login","parameters":[],"requestBody":{"required":true,"content":{"application/json":{"schema":{"$ref":"#/components/schemas/VerifyOtpDto"}}}},"responses":{"201":{"description":""}},"tags":["Customer / Auth"]}},"/api/customer/auth/subscriber-login":{"post":{"operationId":"CustomerAuthController_subscriberLogin","parameters":[],"requestBody":{"required":true,"content":{"application/json":{"schema":{"$ref":"#/components/schemas/SubscriberLoginDto"}}}},"responses":{"201":{"description":""}},"tags":["Customer / Auth"]}},"/api/customer/me":{"get":{"operationId":"CustomerAuthController_getMe","parameters":[],"responses":{"200":{"description":""}},"tags":["Customer / Auth"]},"patch":{"operationId":"CustomerAuthController_updateMe","parameters":[],"requestBody":{"required":true,"content":{"application/json":{"schema":{"$ref":"#/components/schemas/UpdateUserDto"}}}},"responses":{"200":{"description":""}},"tags":["Customer / Auth"]}},"/api/customer/orders":{"post":{"operationId":"CustomerOrdersController_createOrder","parameters":[],"requestBody":{"required":true,"content":{"application/json":{"schema":{"$ref":"#/components/schemas/CreateOrderDto"}}}},"responses":{"201":{"description":""}},"security":[{"bearer":[]}],"tags":["Customer / Orders"]},"get":{"operationId":"CustomerOrdersController_listOrders","parameters":[{"name":"page","required":false,"in":"query","schema":{"default":1,"type":"number"}},{"name":"size","required":false,"in":"query","schema":{"default":20,"type":"number"}},{"name":"q","required":false,"in":"query","schema":{"type":"string"}},{"name":"createdBy","required":false,"in":"query","schema":{"type":"string"}},{"name":"types","required":false,"in":"query","schema":{"type":"array","items":{"type":"string"}}}],"responses":{"200":{"description":""}},"security":[{"bearer":[]}],"tags":["Customer / Orders"]}},"/api/customer/orders/{code}":{"get":{"operationId":"CustomerOrdersController_getOrder","parameters":[{"name":"code","required":true,"in":"path","schema":{"type":"string"}}],"responses":{"200":{"description":""}},"security":[{"bearer":[]}],"tags":["Customer / Orders"]},"delete":{"operationId":"CustomerOrdersController_cancelOrder","parameters":[{"name":"code","required":true,"in":"path","schema":{"type":"string"}}],"responses":{"200":{"description":""}},"security":[{"bearer":[]}],"tags":["Customer / Orders"]}},"/api/customer/orders/{code}/return":{"post":{"operationId":"CustomerOrdersController_requestReturn","parameters":[{"name":"code","required":true,"in":"path","schema":{"type":"string"}}],"responses":{"201":{"description":""}},"security":[{"bearer":[]}],"tags":["Customer / Orders"]}},"/api/customer/orders/{code}/payment-page":{"get":{"operationId":"CustomerOrdersController_getPaymentPage","parameters":[{"name":"code","required":true,"in":"path","schema":{"type":"string"}}],"responses":{"200":{"description":""}},"security":[{"bearer":[]}],"tags":["Customer / Orders"]}},"/api/customer/lockers":{"get":{"operationId":"CustomerOrdersController_getLockers","parameters":[],"responses":{"200":{"description":""}},"security":[{"bearer":[]}],"tags":["Customer / Orders"]}},"/api/customer/lockers/{code}":{"get":{"operationId":"CustomerOrdersController_getLocker","parameters":[{"name":"code","required":true,"in":"path","schema":{"type":"string"}}],"responses":{"200":{"description":""}},"security":[{"bearer":[]}],"tags":["Customer / Orders"]}},"/api/customer/storage/fees":{"get":{"operationId":"CustomerOrdersController_getStorageFees","parameters":[{"name":"size","required":true,"in":"query","schema":{"type":"string","enum":["SMALL","MEDIUM","LARGE","XL"]}},{"name":"durationHours","required":true,"in":"query","schema":{"type":"number","enum":[2,6,24,72]}}],"responses":{"200":{"description":""}},"security":[{"bearer":[]}],"tags":["Customer / Orders"]}},"/api/customer/devices":{"post":{"operationId":"CustomerDevicesController_register","parameters":[],"requestBody":{"required":true,"content":{"application/json":{"schema":{"$ref":"#/components/schemas/RegisterDeviceDto"}}}},"responses":{"201":{"description":""}},"security":[{"bearer":[]}],"tags":["Customer / Devices"]}},"/api/partner/auth/request-otp":{"post":{"operationId":"PartnerAuthController_requestOtp","parameters":[],"requestBody":{"required":true,"content":{"application/json":{"schema":{"$ref":"#/components/schemas/RequestOtpDto"}}}},"responses":{"201":{"description":""}},"tags":["Partner / Auth"]}},"/api/partner/auth/login":{"post":{"operationId":"PartnerAuthController_login","parameters":[],"requestBody":{"required":true,"content":{"application/json":{"schema":{"$ref":"#/components/schemas/VerifyOtpDto"}}}},"responses":{"201":{"description":""}},"tags":["Partner / Auth"]}},"/api/partner/auth/api-key":{"post":{"operationId":"PartnerAuthController_generateApiKey","parameters":[],"responses":{"201":{"description":""}},"security":[{"bearer":[]}],"tags":["Partner / Auth"]}},"/api/partner/me":{"get":{"operationId":"PartnerAuthController_getMe","parameters":[],"responses":{"200":{"description":""}},"security":[{"bearer":[]}],"tags":["Partner / Auth"]}},"/api/partner/orders":{"post":{"operationId":"PartnerOrdersController_createOrder","parameters":[],"requestBody":{"required":true,"content":{"application/json":{"schema":{"$ref":"#/components/schemas/CreateOrderDto"}}}},"responses":{"201":{"description":""}},"security":[{"bearer":[]}],"tags":["Partner / Orders"]},"get":{"operationId":"PartnerOrdersController_listOrders","parameters":[{"name":"page","required":false,"in":"query","schema":{"default":1,"type":"number"}},{"name":"size","required":false,"in":"query","schema":{"default":20,"type":"number"}},{"name":"q","required":false,"in":"query","schema":{"type":"string"}},{"name":"createdBy","required":false,"in":"query","schema":{"type":"string"}},{"name":"types","required":false,"in":"query","schema":{"type":"array","items":{"type":"string"}}}],"responses":{"200":{"description":""}},"security":[{"bearer":[]}],"tags":["Partner / Orders"]}},"/api/partner/orders/stats":{"get":{"operationId":"PartnerOrdersController_getStats","parameters":[{"name":"startTime","required":true,"in":"query","schema":{"type":"string"}},{"name":"endTime","required":true,"in":"query","schema":{"type":"string"}}],"responses":{"200":{"description":""}},"security":[{"bearer":[]}],"tags":["Partner / Orders"]}},"/api/partner/orders/{code}":{"get":{"operationId":"PartnerOrdersController_getOrder","parameters":[{"name":"code","required":true,"in":"path","schema":{"type":"string"}}],"responses":{"200":{"description":""}},"security":[{"bearer":[]}],"tags":["Partner / Orders"]}},"/api/partner/orders/{code}/process":{"post":{"operationId":"PartnerOrdersController_processOrder","parameters":[{"name":"code","required":true,"in":"path","schema":{"type":"string"}}],"requestBody":{"required":true,"content":{"application/json":{"schema":{"$ref":"#/components/schemas/ProcessOrderDto"}}}},"responses":{"201":{"description":""}},"security":[{"bearer":[]}],"tags":["Partner / Orders"]}},"/api/partner/orders/{code}/select-locker":{"put":{"operationId":"PartnerOrdersController_selectLocker","parameters":[{"name":"code","required":true,"in":"path","schema":{"type":"string"}}],"requestBody":{"required":true,"content":{"application/json":{"schema":{"$ref":"#/components/schemas/SelectLockerDto"}}}},"responses":{"200":{"description":""}},"security":[{"bearer":[]}],"tags":["Partner / Orders"]}},"/api/partner/orders/{code}/fake-door":{"post":{"operationId":"PartnerOrdersController_fakeDoor","parameters":[{"name":"code","required":true,"in":"path","schema":{"type":"string"}}],"responses":{"201":{"description":""}},"security":[{"bearer":[]}],"tags":["Partner / Orders"]}},"/api/partner/lockers":{"get":{"operationId":"PartnerOrdersController_getLockers","parameters":[],"responses":{"200":{"description":""}},"security":[{"bearer":[]}],"tags":["Partner / Orders"]}},"/api/partner/lockers/{code}":{"get":{"operationId":"PartnerOrdersController_getLocker","parameters":[{"name":"code","required":true,"in":"path","schema":{"type":"string"}}],"responses":{"200":{"description":""}},"security":[{"bearer":[]}],"tags":["Partner / Orders"]}},"/api/partner/fees":{"get":{"operationId":"PartnerOrdersController_calculateFees","parameters":[{"name":"orderType","required":true,"in":"query","schema":{"type":"string","enum":["PARTNER_LOC","PARTNER_2LOC"]}},{"name":"size","required":false,"in":"query","schema":{"type":"string","enum":["SMALL","MEDIUM","LARGE","XL"]}}],"responses":{"200":{"description":""}},"security":[{"bearer":[]}],"tags":["Partner / Orders"]}},"/api/partner/webhooks":{"get":{"operationId":"PartnerWebhooksController_list","parameters":[],"responses":{"200":{"description":""}},"security":[{"bearer":[]}],"tags":["Partner / Webhooks"]},"post":{"operationId":"PartnerWebhooksController_create","parameters":[],"requestBody":{"required":true,"content":{"application/json":{"schema":{"$ref":"#/components/schemas/CreateWebhookDto"}}}},"responses":{"201":{"description":""}},"security":[{"bearer":[]}],"tags":["Partner / Webhooks"]}},"/api/partner/webhooks/{id}":{"put":{"operationId":"PartnerWebhooksController_update","parameters":[{"name":"id","required":true,"in":"path","schema":{"type":"number"}}],"requestBody":{"required":true,"content":{"application/json":{"schema":{"$ref":"#/components/schemas/UpdateWebhookDto"}}}},"responses":{"200":{"description":""}},"security":[{"bearer":[]}],"tags":["Partner / Webhooks"]},"delete":{"operationId":"PartnerWebhooksController_remove","parameters":[{"name":"id","required":true,"in":"path","schema":{"type":"number"}}],"responses":{"200":{"description":""}},"security":[{"bearer":[]}],"tags":["Partner / Webhooks"]}},"/api/agent/auth/request-otp":{"post":{"operationId":"AgentAuthController_requestOtp","parameters":[],"requestBody":{"required":true,"content":{"application/json":{"schema":{"$ref":"#/components/schemas/RequestOtpDto"}}}},"responses":{"201":{"description":""}},"tags":["Agent / Auth"]}},"/api/agent/auth/login":{"post":{"operationId":"AgentAuthController_login","parameters":[],"requestBody":{"required":true,"content":{"application/json":{"schema":{"$ref":"#/components/schemas/VerifyOtpDto"}}}},"responses":{"201":{"description":""}},"tags":["Agent / Auth"]}},"/api/agent/me":{"get":{"operationId":"AgentAuthController_getMe","parameters":[],"responses":{"200":{"description":""}},"security":[{"bearer":[]}],"tags":["Agent / Auth"]}},"/api/agent/devices":{"post":{"operationId":"AgentAuthController_registerDevice","parameters":[],"requestBody":{"required":true,"content":{"application/json":{"schema":{"$ref":"#/components/schemas/RegisterDeviceDto"}}}},"responses":{"201":{"description":""}},"security":[{"bearer":[]}],"tags":["Agent / Auth"]}},"/api/admin/partners":{"get":{"operationId":"AdminController_listPartners","parameters":[{"name":"x-admin-key","in":"header","description":"ADMIN_API_KEY env var","required":true,"schema":{"type":"string"}}],"responses":{"200":{"description":""}},"summary":"List all partners","tags":["Admin"]},"post":{"operationId":"AdminController_onboardPartner","parameters":[{"name":"x-admin-key","in":"header","description":"ADMIN_API_KEY env var","required":true,"schema":{"type":"string"}}],"requestBody":{"required":true,"content":{"application/json":{"schema":{"$ref":"#/components/schemas/OnboardPartnerDto"}}}},"responses":{"201":{"description":""}},"summary":"Onboard a new partner — returns plain API key once","tags":["Admin"]}},"/api/admin/partners/{code}":{"get":{"operationId":"AdminController_getPartner","parameters":[{"name":"x-admin-key","in":"header","description":"ADMIN_API_KEY env var","required":true,"schema":{"type":"string"}},{"name":"code","required":true,"in":"path","schema":{"type":"string"}}],"responses":{"200":{"description":""}},"summary":"Get a partner by code","tags":["Admin"]}},"/api/admin/lockers":{"get":{"operationId":"AdminController_listLockers","parameters":[{"name":"x-admin-key","in":"header","description":"ADMIN_API_KEY env var","required":true,"schema":{"type":"string"}}],"responses":{"200":{"description":""}},"summary":"List all locker terminals (including inactive)","tags":["Admin"]},"post":{"operationId":"AdminController_createLocker","parameters":[{"name":"x-admin-key","in":"header","description":"ADMIN_API_KEY env var","required":true,"schema":{"type":"string"}}],"requestBody":{"required":true,"content":{"application/json":{"schema":{"$ref":"#/components/schemas/CreateLockerDto"}}}},"responses":{"201":{"description":""}},"summary":"Register a new locker terminal","tags":["Admin"]}},"/api/admin/lockers/{code}":{"patch":{"operationId":"AdminController_updateLocker","parameters":[{"name":"x-admin-key","in":"header","description":"ADMIN_API_KEY env var","required":true,"schema":{"type":"string"}},{"name":"code","required":true,"in":"path","schema":{"type":"string"}}],"requestBody":{"required":true,"content":{"application/json":{"schema":{"$ref":"#/components/schemas/UpdateLockerDto"}}}},"responses":{"200":{"description":""}},"summary":"Update a locker terminal (partial)","tags":["Admin"]}},"/api/admin/users/{id}/subscription":{"patch":{"operationId":"AdminController_setSubscription","parameters":[{"name":"x-admin-key","in":"header","description":"ADMIN_API_KEY env var","required":true,"schema":{"type":"string"}},{"name":"id","required":true,"in":"path","schema":{"type":"string"}}],"requestBody":{"required":true,"content":{"application/json":{"schema":{"$ref":"#/components/schemas/SetSubscriptionDto"}}}},"responses":{"200":{"description":""}},"summary":"Grant or revoke subscriber access for a user","tags":["Admin"]}},"/api/admin/orders":{"get":{"operationId":"AdminController_listOrders","parameters":[{"name":"x-admin-key","in":"header","description":"ADMIN_API_KEY env var","required":true,"schema":{"type":"string"}},{"name":"page","required":true,"in":"query","schema":{"type":"string"}},{"name":"size","required":true,"in":"query","schema":{"type":"string"}},{"name":"q","required":true,"in":"query","schema":{"type":"string"}}],"responses":{"200":{"description":""}},"summary":"List all orders with pagination and filters","tags":["Admin"]}},"/api/admin/orders/stats":{"get":{"operationId":"AdminController_getOrderStats","parameters":[{"name":"x-admin-key","in":"header","description":"ADMIN_API_KEY env var","required":true,"schema":{"type":"string"}},{"name":"startTime","required":true,"in":"query","schema":{"type":"string"}},{"name":"endTime","required":true,"in":"query","schema":{"type":"string"}}],"responses":{"200":{"description":""}},"summary":"Get order statistics for a date range","tags":["Admin"]}},"/api/admin/users":{"get":{"operationId":"AdminController_listUsers","parameters":[{"name":"x-admin-key","in":"header","description":"ADMIN_API_KEY env var","required":true,"schema":{"type":"string"}},{"name":"page","required":true,"in":"query","schema":{"type":"string"}},{"name":"size","required":true,"in":"query","schema":{"type":"string"}},{"name":"roleId","required":true,"in":"query","schema":{"type":"string"}},{"name":"q","required":true,"in":"query","schema":{"type":"string"}}],"responses":{"200":{"description":""}},"summary":"List all users with optional role filter","tags":["Admin"]}},"/api/admin/staff":{"get":{"operationId":"AdminController_listStaff","parameters":[{"name":"x-admin-key","in":"header","description":"ADMIN_API_KEY env var","required":true,"schema":{"type":"string"}}],"responses":{"200":{"description":""}},"summary":"List all kiosk staff across all units","tags":["Admin"]}},"/api/admin/payments":{"get":{"operationId":"AdminController_listPayments","parameters":[{"name":"x-admin-key","in":"header","description":"ADMIN_API_KEY env var","required":true,"schema":{"type":"string"}},{"name":"page","required":true,"in":"query","schema":{"type":"string"}},{"name":"size","required":true,"in":"query","schema":{"type":"string"}}],"responses":{"200":{"description":""}},"summary":"List all payment requests with pagination","tags":["Admin"]}},"/api/admin/agents":{"get":{"operationId":"AdminController_listAgents","parameters":[{"name":"x-admin-key","in":"header","description":"ADMIN_API_KEY env var","required":true,"schema":{"type":"string"}},{"name":"page","required":true,"in":"query","schema":{"type":"string"}},{"name":"size","required":true,"in":"query","schema":{"type":"string"}},{"name":"q","required":true,"in":"query","schema":{"type":"string"}}],"responses":{"200":{"description":""}},"summary":"List all agent users (role=AGENT)","tags":["Admin"]}},"/health":{"get":{"operationId":"HealthController_check","parameters":[],"responses":{"200":{"description":"The Health Check is successful","content":{"application/json":{"schema":{"type":"object","properties":{"status":{"type":"string","example":"ok"},"info":{"type":"object","example":{"database":{"status":"up"}},"additionalProperties":{"type":"object","required":["status"],"properties":{"status":{"type":"string"}},"additionalProperties":true},"nullable":true},"error":{"type":"object","example":{},"additionalProperties":{"type":"object","required":["status"],"properties":{"status":{"type":"string"}},"additionalProperties":true},"nullable":true},"details":{"type":"object","example":{"database":{"status":"up"}},"additionalProperties":{"type":"object","required":["status"],"properties":{"status":{"type":"string"}},"additionalProperties":true}}}}}}},"503":{"description":"The Health Check is not successful","content":{"application/json":{"schema":{"type":"object","properties":{"status":{"type":"string","example":"error"},"info":{"type":"object","example":{"database":{"status":"up"}},"additionalProperties":{"type":"object","required":["status"],"properties":{"status":{"type":"string"}},"additionalProperties":true},"nullable":true},"error":{"type":"object","example":{"redis":{"status":"down","message":"Could not connect"}},"additionalProperties":{"type":"object","required":["status"],"properties":{"status":{"type":"string"}},"additionalProperties":true},"nullable":true},"details":{"type":"object","example":{"database":{"status":"up"},"redis":{"status":"down","message":"Could not connect"}},"additionalProperties":{"type":"object","required":["status"],"properties":{"status":{"type":"string"}},"additionalProperties":true}}}}}}}},"tags":["Health"]}},"/external/winnsen-playground":{"get":{"operationId":"ExternalController_getWinnsenPlayground","parameters":[],"responses":{"200":{"description":""}},"summary":"Winnsen integration test playground","tags":["External"]}},"/external/dev-otp":{"get":{"operationId":"ExternalController_getDevOtpPage","parameters":[],"responses":{"200":{"description":""}},"summary":"Dev OTP lookup page (dev only)","tags":["External"]}},"/external/dev/request-otp":{"post":{"operationId":"ExternalController_devRequestOtp","parameters":[],"requestBody":{"required":true,"content":{"application/json":{"schema":{"$ref":"#/components/schemas/DevRequestOtpDto"}}}},"responses":{"201":{"description":""}},"summary":"Generate and return OTP for testing (dev only)","tags":["External"]}},"/external/dev/notify":{"post":{"operationId":"ExternalController_devNotify","parameters":[],"requestBody":{"required":true,"content":{"application/json":{"schema":{"$ref":"#/components/schemas/DevNotifyDto"}}}},"responses":{"201":{"description":""}},"summary":"Send test notification via SMS, WhatsApp, or both (dev only)","tags":["External"]}},"/api/v1/devices/register":{"post":{"operationId":"KioskController_register","parameters":[],"requestBody":{"required":true,"content":{"application/json":{"schema":{"$ref":"#/components/schemas/RegisterDeviceDto"}}}},"responses":{"201":{"description":"Device registered, token returned once"},"404":{"description":"unit_id not found"},"409":{"description":"serial_number already registered"}},"summary":"Register a new kiosk tablet","tags":["kiosk"]}},"/api/v1/devices/{deviceId}/heartbeat":{"put":{"operationId":"KioskController_heartbeat","parameters":[{"name":"deviceId","required":true,"in":"path","schema":{"type":"string"}}],"requestBody":{"required":true,"content":{"application/json":{"schema":{"$ref":"#/components/schemas/HeartbeatDto"}}}},"responses":{"204":{"description":""}},"security":[{"bearer":[]}],"summary":"Device heartbeat — update last seen + connectivity","tags":["kiosk"]}},"/api/v1/devices/{deviceId}/config":{"get":{"operationId":"KioskController_getConfig","parameters":[{"name":"deviceId","required":true,"in":"path","schema":{"type":"string"}}],"responses":{"200":{"description":""}},"security":[{"bearer":[]}],"summary":"Get device configuration and active QR public keys","tags":["kiosk"]}},"/api/v1/devices/{deviceId}/users":{"get":{"operationId":"KioskController_getUsers","parameters":[{"name":"deviceId","required":true,"in":"path","schema":{"type":"string"}},{"name":"updated_since","required":false,"in":"query","description":"ISO timestamp — omit for full sync","schema":{"type":"string"}}],"responses":{"200":{"description":""}},"security":[{"bearer":[]}],"summary":"Sync authorised users (delta or full)","tags":["kiosk"]}},"/api/v1/devices/{deviceId}/lockers":{"get":{"operationId":"KioskController_getLockers","parameters":[{"name":"deviceId","required":true,"in":"path","schema":{"type":"string"}},{"name":"updated_since","required":false,"in":"query","description":"ISO timestamp — omit for full sync","schema":{"type":"string"}}],"responses":{"200":{"description":""}},"security":[{"bearer":[]}],"summary":"Sync locker slot definitions (delta or full)","tags":["kiosk"]}},"/api/v1/devices/{deviceId}/keys":{"get":{"operationId":"KioskController_getPublicKeys","parameters":[{"name":"deviceId","required":true,"in":"path","schema":{"type":"string"}}],"responses":{"200":{"description":""}},"security":[{"bearer":[]}],"summary":"Get active RSA public keys for offline QR verification","tags":["kiosk"]}},"/api/v1/devices/{deviceId}/events":{"post":{"operationId":"KioskController_uploadEvents","parameters":[{"name":"deviceId","required":true,"in":"path","schema":{"type":"string"}}],"requestBody":{"required":true,"content":{"application/json":{"schema":{"$ref":"#/components/schemas/UploadEventsDto"}}}},"responses":{"200":{"description":"accepted/rejected lists"}},"security":[{"bearer":[]}],"summary":"Batch upload locker audit events from tablet","tags":["kiosk"]}},"/api/v1/devices/{deviceId}/staff":{"get":{"operationId":"KioskController_getStaff","parameters":[{"name":"deviceId","required":true,"in":"path","schema":{"type":"string"}},{"name":"updated_since","required":false,"in":"query","description":"ISO timestamp — omit for full sync","schema":{"type":"string"}}],"responses":{"200":{"description":""}},"security":[{"bearer":[]}],"summary":"Sync staff accounts for offline auth (delta or full)","tags":["kiosk"]},"post":{"operationId":"KioskController_createStaff","parameters":[{"name":"deviceId","required":true,"in":"path","schema":{"type":"string"}}],"requestBody":{"required":true,"content":{"application/json":{"schema":{"$ref":"#/components/schemas/CreateKioskStaffDto"}}}},"responses":{"201":{"description":""}},"security":[{"bearer":[]}],"summary":"Create a new staff member for this locker unit","tags":["kiosk"]}},"/api/v1/devices/{deviceId}/staff/{staffId}":{"patch":{"operationId":"KioskController_updateStaff","parameters":[{"name":"deviceId","required":true,"in":"path","schema":{"type":"string"}},{"name":"staffId","required":true,"in":"path","schema":{"type":"string"}}],"requestBody":{"required":true,"content":{"application/json":{"schema":{"$ref":"#/components/schemas/UpdateKioskStaffDto"}}}},"responses":{"200":{"description":""}},"security":[{"bearer":[]}],"summary":"Update a staff member (name, role, PIN, active)","tags":["kiosk"]},"delete":{"operationId":"KioskController_deleteStaff","parameters":[{"name":"deviceId","required":true,"in":"path","schema":{"type":"string"}},{"name":"staffId","required":true,"in":"path","schema":{"type":"string"}}],"responses":{"200":{"description":""}},"security":[{"bearer":[]}],"summary":"Deactivate a staff member (soft delete)","tags":["kiosk"]}}},"info":{"title":"LocQar API","description":"LocQar Smart Locker Platform — NestJS Monolith","version":"1.0","contact":{}},"tags":[],"servers":[],"components":{"securitySchemes":{"bearer":{"scheme":"bearer","bearerFormat":"JWT","type":"http"}},"schemas":{"CreatePaymentRequestDto":{"type":"object","properties":{"orderCode":{"type":"string","description":"Order code"},"amount":{"type":"number","description":"Amount in pesewas (smallest GHS unit)"},"currencyCode":{"type":"string","description":"Currency code (GHS or USD)"}},"required":["orderCode","amount"]},"WinnsenActionDto":{"type":"object","properties":{"action":{"type":"string","example":"order-dropoff"},"lockerSN":{"type":"string"},"owner":{"type":"string"},"doorNum":{"type":"number"},"timestamp":{"type":"number"},"phone":{"type":"string"},"password":{"type":"string"},"qrToken":{"type":"string"},"studentId":{"type":"string"},"agentId":{"type":"string"},"subscriberId":{"type":"string"},"orderNumber":{"type":"string"},"boxSN":{"type":"string"},"doorOpenCode":{"type":"string"},"storageSize":{"type":"string"},"storageDurationHours":{"type":"number"}},"required":["action"]},"OpenDoorDto":{"type":"object","properties":{}},"AckCommandDto":{"type":"object","properties":{}},"RequestOtpDto":{"type":"object","properties":{"phone":{"type":"string","example":"0244000001"},"role":{"type":"string","enum":["CUSTOMER","PARTNER","AGENT","ADMIN"],"example":"CUSTOMER"}},"required":["phone","role"]},"VerifyOtpDto":{"type":"object","properties":{"phone":{"type":"string","example":"0244000001"},"otp":{"type":"string","example":"123456"},"role":{"type":"string","enum":["CUSTOMER","PARTNER","AGENT","ADMIN"]}},"required":["phone","otp","role"]},"SubscriberLoginDto":{"type":"object","properties":{"studentId":{"type":"string"},"password":{"type":"string"}},"required":["studentId","password"]},"UpdateUserDto":{"type":"object","properties":{"name":{"type":"string"},"email":{"type":"string"}}},"CreateOrderDto":{"type":"object","properties":{"code":{"type":"string"},"type":{"type":"string","enum":["PARTNER_LOC","PARTNER_2LOC","CUS_1LOC","CUS_2LOC"]},"desLockerCode":{"type":"string"},"srcLockerCode":{"type":"string"},"recipientPhoneNumber":{"type":"string"},"senderPhoneNumber":{"type":"string"},"description":{"type":"string"},"doorToDoorEnabled":{"type":"boolean"},"pickupPaymentEnabled":{"type":"boolean"},"dropOffPaymentEnabled":{"type":"boolean"},"storageSize":{"type":"string","enum":["SMALL","MEDIUM","LARGE","XL"]},"storageDurationHours":{"type":"number","enum":[2,6,24,72],"description":"Must be 2, 6, 24, or 72"}},"required":["code","type","desLockerCode","recipientPhoneNumber"]},"RegisterDeviceDto":{"type":"object","properties":{"serial_number":{"type":"string","example":"SN-12345678"},"unit_id":{"type":"string","example":"uuid-of-locker-unit"},"app_version":{"type":"string","example":"1.0.0"},"android_version":{"type":"string","example":"13"},"model":{"type":"string","example":"Samsung Galaxy Tab A8"}},"required":["serial_number","unit_id","app_version"]},"ProcessOrderDto":{"type":"object","properties":{"event":{"type":"string","enum":["CONFIRMED","LOCKER_AGENT_DROPOFF","LOCKER_GUEST_DROPOFF","LOCKER_SUBSCRIBER_DROPOFF","LOCKER_AGENT_COLLECT","LOCKER_GUEST_COLLECT","LOCKER_SUBSCRIBER_COLLECT","CANCELED","RECALL_REQUESTED","RETURN_REQUESTED","LOCKER_SELECTED"]},"lockerCode":{"type":"string"},"lockerDoorNo":{"type":"string"},"lockerSize":{"type":"string"},"lockerPinCode":{"type":"string"},"senderPhoneNumber":{"type":"string"},"description":{"type":"string"}},"required":["event"]},"SelectLockerDto":{"type":"object","properties":{"srcLockerCode":{"type":"string"}},"required":["srcLockerCode"]},"CreateWebhookDto":{"type":"object","properties":{"webhookUrl":{"type":"string"},"secret":{"type":"string"},"scopes":{"example":["order.created","order.status_updated"],"type":"array","items":{"type":"array"}}},"required":["webhookUrl","secret","scopes"]},"UpdateWebhookDto":{"type":"object","properties":{"webhookUrl":{"type":"string"},"secret":{"type":"string"},"scopes":{"type":"array","items":{"type":"array"}}}},"OnboardPartnerDto":{"type":"object","properties":{"name":{"type":"string","example":"Jumia Ghana"},"code":{"type":"string","example":"JUMIA-GH","description":"Unique slug — uppercase letters, digits, hyphens"},"phone":{"type":"string","example":"+233201234567"}},"required":["name","code","phone"]},"CreateLockerDto":{"type":"object","properties":{"code":{"type":"string","example":"ACCRA-MALL-01"},"name":{"type":"string","example":"Accra Mall — Bay 1"},"serialNumber":{"type":"string","example":"WINNSEN-SN-001","description":"Winnsen hardware serial number"},"location":{"type":"string","example":"Accra Mall, Spintex Road, Accra"},"description":{"type":"string"},"latitude":{"type":"number","example":5.6037},"longitude":{"type":"number","example":-0.187}},"required":["code","name","serialNumber","location"]},"UpdateLockerDto":{"type":"object","properties":{"name":{"type":"string"},"serialNumber":{"type":"string"},"location":{"type":"string"},"description":{"type":"string"},"latitude":{"type":"number"},"longitude":{"type":"number"},"active":{"type":"boolean"}}},"SetSubscriptionDto":{"type":"object","properties":{"isSubscriber":{"type":"boolean"},"studentId":{"type":"string","description":"Student / subscriber ID for kiosk login"}},"required":["isSubscriber"]},"DevRequestOtpDto":{"type":"object","properties":{"phone":{"type":"string","example":"+233244000001"},"role":{"type":"string","enum":["CUSTOMER","PARTNER","AGENT","ADMIN"],"default":"CUSTOMER"}},"required":["phone","role"]},"DevNotifyDto":{"type":"object","properties":{"phone":{"type":"string","example":"0530959201"},"message":{"type":"string","example":"LocQar: Your pickup PIN is 1234."},"channel":{"type":"string","enum":["sms","whatsapp","both"],"default":"both"}},"required":["phone","message","channel"]},"HeartbeatDto":{"type":"object","properties":{"app_version":{"type":"string","example":"1.0.0"},"connectivity":{"type":"string","example":"online"},"usb_connected":{"type":"boolean"},"pending_events":{"type":"number","example":3},"last_sync_at":{"type":"string"}},"required":["app_version","connectivity","usb_connected","pending_events"]},"EventDto":{"type":"object","properties":{"id":{"type":"string"},"locker_id":{"type":"string"},"user_id":{"type":"string"},"event_type":{"type":"string","enum":["OPEN","CLOSE","FAULT","AUTH_FAIL","LOCKOUT","SYNC","ADMIN_OVERRIDE","HARDWARE_RECONNECT"]},"auth_method":{"type":"string","enum":["PIN","QR","ADMIN","NONE"]},"occurred_at":{"type":"string"},"metadata":{"type":"object"}},"required":["id","locker_id","event_type","auth_method","occurred_at"]},"UploadEventsDto":{"type":"object","properties":{"events":{"type":"array","items":{"$ref":"#/components/schemas/EventDto"}}},"required":["events"]},"CreateKioskStaffDto":{"type":"object","properties":{"name":{"type":"string","example":"Kwame"},"pin":{"type":"string","example":"5678","description":"Plain 4-6 digit PIN — hashed server-side"},"role":{"type":"string","enum":["MANAGER","TECHNICIAN","ATTENDANT"],"example":"TECHNICIAN"}},"required":["name","pin","role"]},"UpdateKioskStaffDto":{"type":"object","properties":{"name":{"type":"string","example":"Kwame Asante"},"pin":{"type":"string","example":"9999","description":"New PIN (omit to keep current)"},"role":{"type":"string","enum":["MANAGER","TECHNICIAN","ATTENDANT"]},"active":{"type":"boolean"}}}}}}